mmcv_geo/__init__.py
mmcv_geo/image/__init__.py
mmcv_geo/image/io.py
mmcv_geo-0.1.2.dist-info/METADATA
mmcv_geo-0.1.2.dist-info/WHEEL
mmcv_geo-0.1.2.dist-info/RECORD
